Workbook

Sheet Sheet1
A1: Company | B1: Location | C1: $Name | D1: Sales Person | E1: Credit Period | F1: Credit Limit | G1: Openning Apr-25
A2: Enterprise | B2: Noida | C2: A N CREATION | D2: KHURSHID JI | E2: 45 Days | F2: 800000 | G2: 0
A3: O-tec | B3: Noida | C3: A N CREATION | D3: KHURSHID JI | E3: 45 Days | F3: 800000 | G3: 86376
A4: O-tec | B4: Surat | C4: A N CREATION | D4: KHURSHID JI | F4: 0 | G4: 0
A5: Enterprise | B5: Surat | C5: A S TRADING | D5: OTHERS | E5: 60 Days | F5: 0 | G5: 0
A6: O-tec | B6: Surat | C6: A S TRADING | D6: OTHERS | F6: 0 | G6: 0
A7: O-tec | B7: Surat | C7: A.I DIGITAL PRINT | D7: PURAV SHAH | E7: 45 Days | F7: 350000 | G7: 0
A8: O-tec | B8: Surat | C8: A.N.CREATION - MACHINE | D8: KHURSHID JI | F8: 0 | G8: 0
A9: Enterprise | B9: Noida | C9: AAD SACH CREATIONS | D9: OTHERS | F9: 0 | G9: 0
A10: O-tec | B10: Surat | C10: AAD SACH CREATIONS | D10: OTHERS | F10: 0 | G10: -500000
A11: O-tec | B11: Noida | C11: AAD SACH CREATIONS | D11: OTHERS | F11: 0 | G11: 0
A12: Enterprise | B12: Surat | C12: AADESH DIGITAL PRINTS | D12: PURAV SHAH | E12: 60 | F12: 50000 | G12: 0
A13: O-tec | B13: Surat | C13: AADESH DIGITAL PRINTS | D13: PURAV SHAH | E13: 60 Days | F13: 500000 | G13: 515011
A14: O-tec | B14: Surat | C14: AADESH DIGITAL PRINTS-MACHINE | D14: PURAV SHAH | F14: 0 | G14: 0
A15: O-tec | B15: Surat | C15: AAKASH FASHION PRINTS PVT LTD | D15: DHANANJAY | E15: 2 Days | F15: 1500000 | G15: 1047132
A16: O-tec | B16: Surat | C16: AAKASH FASHION PRINTS PVT LTD- MACHINE | D16: DHANANJAY | F16: 0 | G16: 0
A17: O-tec | B17: Surat | C17: AAR KAY GRAPHICS | D17: OTHERS | F17: 0 | G17: 0
A18: O-tec | B18: Surat | C18: AARNA FASHION | D18: OTHERS | E18: 45 Days | F18: 950000 | G18: 0
A19: Enterprise | B19: Surat | C19: AARNAV FASHIONS LIMITED | D19: NAKUL JI | E19: 7 Days | F19: 2500000 | G19: 0
A20: O-tec | B20: Surat | C20: AARNAV FASHIONS LIMITED | D20: NAKUL JI | E20: 60 Days | F20: 7200000 | G20: 1041254
A21: O-tec | B21: Surat | C21: AARNAV FASHIONS LIMITED-Machine | D21: NAKUL JI | F21: 0 | G21: 0
A22: O-tec | B22: Surat | C22: AASIYA CREATION | D22: OTHERS | E22: 45 Days | F22: 400000 | G22: 0
A23: O-tec | B23: Noida | C23: AAYUSH RATHI | D23: OTHERS | F23: 0 | G23: 0
A24: O-tec | B24: Surat | C24: AAYUSH SIR | D24: OTHERS | F24: 0 | G24: 0
A25: O-tec | B25: Surat | C25: ABHISEKH TEXCHEM PVT LTD. | D25: OTHERS | F25: 0 | G25: 0
A26: O-tec | B26: Surat | C26: ABHISEKH TEXCHEM PVT LTD-MACHINE | D26: OTHERS | F26: 0 | G26: 300000
A27: O-tec | B27: Surat | C27: ACCRUED REVENUE | D27: OTHERS | F27: 0 | G27: 2534400
A28: O-tec | B28: Surat | C28: ACS TEXTILES (BANGLADESH) LTD | D28: OTHERS | F28: 0 | G28: 0
A29: Enterprise | B29: Surat | C29: ADIYA DESIGNER | D29: NAKUL JI | E29: 60 Days | F29: 100000 | G29: 0
A30: O-tec | B30: Surat | C30: ADIYA DESIGNER | D30: NAKUL JI | E30: 60 Days | F30: 4000000 | G30: 2502447
A31: O-tec | B31: Surat | C31: ADVANCE FORM DEBTORS | D31: OTHERS | F31: 0 | G31: -1956
A32: O-tec | B32: Surat | C32: AEROLAM DECORATIVES LLP | D32: OTHERS | F32: 0 | G32: 0
A33: O-tec | B33: Surat | C33: AGANSA PRIMATAMA. PT | D33: OTHERS | F33: 0 | G33: 0
A34: O-tec | B34: Surat | C34: AIRDOT FAB TEX | D34: OTHERS | F34: 0 | G34: 0
A35: O-tec | B35: Surat | C35: AISHAWARYA CREATIONS | D35: MANMOHAN JI | E35: 30 Days | F35: 600000 | G35: 25025
A36: O-tec | B36: Noida | C36: AISHAWARYA CREATIONS | D36: MANMOHAN JI | E36: 30 Days | F36: 1241782 | G36: 186735
A37: Enterprise | B37: Surat | C37: AJANTA DIGITAL INDUSTRIES | D37: DHANANJAY | F37: 300000 | G37: 0
A38: O-tec | B38: Surat | C38: AJANTA DIGITAL INDUSTRIES-AHMEDABAD | D38: DHANANJAY | F38: 0 | G38: 0
A39: O-tec | B39: Surat | C39: AJANTA DIGITAL INDUSTRIES-SURAT | D39: DHANANJAY | F39: 650000 | G39: 0
A40: O-tec | B40: Surat | C40: AKASH PRASANNAKUMAR SHAH- DOLPHIN DIGITAL | D40: OTHERS | F40: 0 | G40: 0
A41: O-tec | B41: Surat | C41: AKHAND DIGITEX | D41: OTHERS | E41: 15 Days | F41: 450000 | G41: 0
A42: O-tec | B42: Surat | C42: AKLAVYA INDUSTRIES PVT.LTD. | D42: OTHERS | E42: 30 Days | F42: 0 | G42: 0
A43: O-tec | B43: Surat | C43: AKSHAR PRINTS | D43: OTHERS | F43: 0 | G43: 0
A44: O-tec | B44: Surat | C44: AKSHAR PRINTS-MACHINE | D44: OTHERS | F44: 0 | G44: 0
A45: O-tec | B45: Surat | C45: ALOK FABRICS | D45: DHANANJAY | E45: 60 Days | F45: 550000 | G45: 40710
A46: O-tec | B46: Noida | C46: ALOK TEXTILE MILL | D46: KHURSHID JI | F46: 0 | G46: 0
A47: O-tec | B47: Surat | C47: ALOKA EXPORTS | D47: OTHERS | F47: 1210000 | G47: -510328
A48: O-tec | B48: Noida | C48: ALOKA EXPORTS | D48: OTHERS | F48: 0 | G48: 0
A49: O-tec | B49: Surat | C49: ALPHA DIGITAL | D49: OTHERS | F49: 4000 | G49: 0
A50: Enterprise | B50: Noida | C50: AMAAYRA DIGITAL PRIVATE LIMITED | D50: MANMOHAN JI | F50: 0 | G50: 0
A51: O-tec | B51: Noida | C51: AMAAYRA DIGITAL PRIVATE LIMITED | D51: MANMOHAN JI | E51: 45 Days | F51: 1989490 | G51: 2085525.5
A52: O-tec | B52: Surat | C52: AMAAYRA DIGITAL PRIVATE LIMITED-MACHINE | D52: MANMOHAN JI | F52: 0 | G52: 0
A53: O-tec | B53: Noida | C53: AMAAYRA DIGITAL PRIVATE LIMITED-MACHINE | D53: MANMOHAN JI | F53: 0 | G53: 2595000
A54: O-tec | B54: Noida | C54: AMANDEEP TEXTILES | D54: MANMOHAN JI | E54: 45 Days | F54: 0 | G54: 0
A55: O-tec | B55: Surat | C55: AMANDEEP TEXTILES-MACHINE | D55: MANMOHAN JI | F55: 0 | G55: 0
A56: O-tec | B56: Surat | C56: AMAR CREATION | D56: PURAV SHAH | F56: 0 | G56: 0
A57: O-tec | B57: Surat | C57: AMARASHA DIGITAL PRINTS PRIVATE LIMITED | D57: NAKUL JI | E57: 30 Days | F57: 900000 | G57: 0
A58: O-tec | B58: Surat | C58: AMARSONS IMPEX | D58: OTHERS | F58: 0 | G58: 0
A59: O-tec | B59: Surat | C59: AMBE TEXTILES | D59: OTHERS | F59: 0 | G59: 0
A60: Enterprise | B60: Noida | C60: AMBIKA INTERNATIONAL | D60: KHURSHID JI | E60: 45 Days | F60: 414745 | G60: 0
A61: Enterprise | B61: Surat | C61: AMBIKA INTERNATIONAL | D61: KHURSHID JI | F61: 0 | G61: 0
A62: O-tec | B62: Surat | C62: AMBIKA INTERNATIONAL | D62: KHURSHID JI | F62: 0 | G62: 0
A63: O-tec | B63: Noida | C63: AMBIKA INTERNATIONAL | D63: KHURSHID JI | E63: 45 Days | F63: 500000 | G63: 0
A64: O-tec | B64: Surat | C64: AMIT CORPORATION | D64: OTHERS | F64: 0 | G64: 0
A65: Enterprise | B65: Surat | C65: AMIT DIGITAL PRINT | D65: NAKUL JI | E65: 1 Days | F65: 300000 | G65: 0
A66: O-tec | B66: Surat | C66: AMIT DIGITAL PRINT | D66: NAKUL JI | F66: 500000 | G66: 0
A67: O-tec | B67: Surat | C67: AMTEX DYE CHEM INDUSTRIES | D67: OTHERS | F67: 0 | G67: 0
A68: O-tec | B68: Noida | C68: ANAND DYERS | D68: MANMOHAN JI | E68: 30 Days | F68: 1807430 | G68: 222060
A69: O-tec | B69: Surat | C69: ANAND DYERS-MACHINE | D69: OTHERS | F69: 2005000 | G69: 0
A70: O-tec | B70: Surat | C70: ANANYA CREATION | D70: OTHERS | F70: 200000 | G70: 137521.34
A71: Enterprise | B71: Surat | C71: ANAYAA DIGITAL LLP | D71: NAKUL JI | E71: 40 Days | F71: 300000 | G71: 0
A72: O-tec | B72: Surat | C72: ANAYAA DIGITAL LLP | D72: NAKUL JI | E72: 40 Days | F72: 1605000 | G72: 575510
A73: O-tec | B73: Surat | C73: ANAYAA DIGITAL LLP(MACHINE) | D73: OTHERS | F73: 0 | G73: 0
A74: O-tec | B74: Surat | C74: ANGARIKA DIGITEX PVT LTD | D74: KARAN SIR | E74: 75 Days | F74: 20000000 | G74: 19419409
A75: O-tec | B75: Surat | C75: ANGARIKA DIGITEX PVT LTD-MACHINE | D75: KARAN SIR | F75: 0 | G75: 0
A76: O-tec | B76: Surat | C76: ANIL | D76: OTHERS | F76: 0 | G76: 0
A77: Enterprise | B77: Surat | C77: ANISHA THE COLOUR CO. | D77: UMESH JI | E77: 15 | F77: 10000000 | G77: 0
A78: O-tec | B78: Surat | C78: ANISHA THE COLOUR CO. | D78: UMESH JI | E78: 15 Days | F78: 10000000 | G78: 1632087
A79: O-tec | B79: Surat | C79: ANISHA THE COLOUR CO.- MACHINE | D79: UMESH JI | F79: 0 | G79: 0
A80: O-tec | B80: Surat | C80: ANJANI SYNTHETICS LIMITED | D80: OTHERS | F80: 182000 | G80: 0
A81: O-tec | B81: Surat | C81: ANJANI SYNTHETICS LIMITED-MACHINE | D81: OTHERS | F81: 0 | G81: 0
A82: O-tec | B82: Surat | C82: ANKIT CREATION | D82: OTHERS | F82: 0 | G82: 0
A83: O-tec | B83: Surat | C83: ANSARI MAKBULALAM MOHMEDYASHIN | D83: OTHERS | F83: 0 | G83: 0
A84: Enterprise | B84: Surat | C84: ANSH DIGITEX LLP | D84: DHANANJAY | E84: 90 Days | F84: 0 | G84: 0
A85: O-tec | B85: Surat | C85: ANSH DIGITEX LLP | D85: DHANANJAY | E85: 90 Days | F85: 1600000 | G85: 0
A86: Enterprise | B86: Surat | C86: ANUPAM CREATION PVT LTD | D86: AAYUSH SIR | E86: 1 | F86: 5100000 | G86: 0
A87: O-tec | B87: Surat | C87: ANUPAM CREATION PVT LTD | D87: AAYUSH SIR | E87: 1 Days | F87: 5100000 | G87: 1874108
A88: O-tec | B88: Noida | C88: ANUPAM CREATION PVT LTD | D88: AAYUSH SIR | E88: 1 Days | F88: 0 | G88: 0
A89: O-tec | B89: Surat | C89: ANUPAM CREATION PVT LTD-MACHINE | D89: AAYUSH SIR | F89: 0 | G89: 0
A90: O-tec | B90: Surat | C90: APEX IMPEX | D90: OTHERS | F90: 200000 | G90: 578630
A91: O-tec | B91: Surat | C91: APEX IMPEX-Amit Digital Prints | D91: OTHERS | F91: 0 | G91: 0
A92: O-tec | B92: Surat | C92: APK ENGINEERING | D92: OTHERS | F92: 0 | G92: 0
A93: Enterprise | B93: Surat | C93: APOLLO DIGITEX PVT.LTD | D93: AAYUSH SIR | E93: 75 | F93: 10000000 | G93: 0
A94: O-tec | B94: Surat | C94: APOLLO DIGITEX PVT.LTD | D94: AAYUSH SIR | E94: 90 Days | F94: 10000000 | G94: 5769248
A95: O-tec | B95: Surat | C95: APOLLO DIGITEX PVT.LTD-MACHINE | D95: AAYUSH SIR | E95: 30 Days | F95: 0 | G95: 2003380
A96: Enterprise | B96: Noida | C96: APOLLO DIGITEX PRIVATE LIMITED | D96: AAYUSH SIR | E96: 90 Days | F96: 950000 | G96: 0
A97: O-tec | B97: Noida | C97: APOLLO DIGITEX PRIVATE LIMITED | D97: AAYUSH SIR | E97: 90 Days | F97: 3085000 | G97: 2124078.9
A98: O-tec | B98: Surat | C98: APSARA SILKS | D98: OTHERS | F98: 63000 | G98: 0
A99: O-tec | B99: Surat | C99: ARA DIGITAL PRINTS | D99: NAKUL JI | E99: 60 Days | F99: 700000 | G99: 0
A100: O-tec | B100: Surat | C100: ARCHNA DYEING & PRINTING MILLS P LTD | D100: OTHERS | E100: 7 Days | F100: 0 | G100: 0
...

Sheet Sheet3
A1: Company | B1: Location | C1: $Name | D1: Sales Person | E1: Credit Period | F1: Credit Limit | G1: Openning Apr-25 | H1: Outstanding
A2: Enterprise | B2: Noida | C2: A N CREATION | D2: KHURSHID JI | E2: 45 Days | F2: 800000 | G2: 0 | H2: {=XLOOKUP(C:C,Sheet3!A:A,Sheet3!B:B)} -> #N/A
A3: O-tec | B3: Noida | C3: A N CREATION | D3: KHURSHID JI | E3: 45 Days | F3: 800000 | G3: 86376 | H3: {=XLOOKUP(C:C,Sheet3!A:A,Sheet3!B:B)} -> #N/A
A4: O-tec | B4: Surat | C4: A N CREATION | D4: KHURSHID JI | F4: 0 | G4: 0 | H4: {=XLOOKUP(C:C,Sheet3!A:A,Sheet3!B:B)} -> #N/A
A5: Enterprise | B5: Surat | C5: A S TRADING | D5: OTHERS | E5: 60 Days | F5: 0 | G5: 0 | H5: {=XLOOKUP(C:C,Sheet3!A:A,Sheet3!B:B)} -> #N/A
A6: O-tec | B6: Surat | C6: A S TRADING | D6: OTHERS | F6: 0 | G6: 0 | H6: {=XLOOKUP(C:C,Sheet3!A:A,Sheet3!B:B)} -> #N/A
A7: O-tec | B7: Surat | C7: A.I DIGITAL PRINT | D7: PURAV SHAH | E7: 45 Days | F7: 350000 | G7: 0 | H7: {=XLOOKUP(C:C,Sheet3!A:A,Sheet3!B:B)} -> #N/A
A8: O-tec | B8: Surat | C8: A.N.CREATION - MACHINE | D8: KHURSHID JI | F8: 0 | G8: 0 | H8: {=XLOOKUP(C:C,Sheet3!A:A,Sheet3!B:B)} -> #N/A
A9: Enterprise | B9: Noida | C9: AAD SACH CREATIONS | D9: OTHERS | F9: 0 | G9: 0 | H9: 0
A10: O-tec | B10: Surat | C10: AAD SACH CREATIONS | D10: OTHERS | F10: 0 | G10: -500000 | H10: 0
A11: O-tec | B11: Noida | C11: AAD SACH CREATIONS | D11: OTHERS | F11: 0 | G11: 0 | H11: 0
A12: Enterprise | B12: Surat | C12: AADESH DIGITAL PRINTS | D12: PURAV SHAH | E12: 60 | F12: 50000 | G12: 0 | H12: {=XLOOKUP(C:C,Sheet3!A:A,Sheet3!B:B)} -> #N/A
A13: O-tec | B13: Surat | C13: AADESH DIGITAL PRINTS | D13: PURAV SHAH | E13: 60 Days | F13: 500000 | G13: 515011 | H13: {=XLOOKUP(C:C,Sheet3!A:A,Sheet3!B:B)} -> #N/A
A14: O-tec | B14: Surat | C14: AADESH DIGITAL PRINTS-MACHINE | D14: PURAV SHAH | F14: 0 | G14: 0 | H14: 0
A15: O-tec | B15: Surat | C15: AAKASH FASHION PRINTS PVT LTD | D15: DHANANJAY | E15: 2 Days | F15: 1500000 | G15: 1047132 | H15: {=XLOOKUP(C:C,Sheet3!A:A,Sheet3!B:B)} -> #N/A
A16: O-tec | B16: Surat | C16: AAKASH FASHION PRINTS PVT LTD- MACHINE | D16: DHANANJAY | F16: 0 | G16: 0 | H16: 0
A17: O-tec | B17: Surat | C17: AAR KAY GRAPHICS | D17: OTHERS | F17: 0 | G17: 0 | H17: 0
A18: O-tec | B18: Surat | C18: AARNA FASHION | D18: OTHERS | E18: 45 Days | F18: 950000 | G18: 0 | H18: {=XLOOKUP(C:C,Sheet3!A:A,Sheet3!B:B)} -> #N/A
A19: Enterprise | B19: Surat | C19: AARNAV FASHIONS LIMITED | D19: NAKUL JI | E19: 7 Days | F19: 2500000 | G19: 0 | H19: {=XLOOKUP(C:C,Sheet3!A:A,Sheet3!B:B)} -> #N/A
A20: O-tec | B20: Surat | C20: AARNAV FASHIONS LIMITED | D20: NAKUL JI | E20: 60 Days | F20: 7200000 | G20: 1041254 | H20: {=XLOOKUP(C:C,Sheet3!A:A,Sheet3!B:B)} -> #N/A
A21: O-tec | B21: Surat | C21: AARNAV FASHIONS LIMITED-Machine | D21: NAKUL JI | F21: 0 | G21: 0 | H21: {=XLOOKUP(C:C,Sheet3!A:A,Sheet3!B:B)} -> #N/A
A22: O-tec | B22: Surat | C22: AASIYA CREATION | D22: OTHERS | E22: 45 Days | F22: 400000 | G22: 0 | H22: {=XLOOKUP(C:C,Sheet3!A:A,Sheet3!B:B)} -> #N/A
A23: O-tec | B23: Noida | C23: AAYUSH RATHI | D23: OTHERS | F23: 0 | G23: 0 | H23: 0
A24: O-tec | B24: Surat | C24: AAYUSH SIR | D24: OTHERS | F24: 0 | G24: 0 | H24: 0
A25: O-tec | B25: Surat | C25: ABHISEKH TEXCHEM PVT LTD. | D25: OTHERS | F25: 0 | G25: 0 | H25: 0
A26: O-tec | B26: Surat | C26: ABHISEKH TEXCHEM PVT LTD-MACHINE | D26: OTHERS | F26: 0 | G26: 300000 | H26: {=XLOOKUP(C:C,Sheet3!A:A,Sheet3!B:B)} -> #N/A
A27: O-tec | B27: Surat | C27: ACCRUED REVENUE | D27: OTHERS | F27: 0 | G27: 2534400 | H27: 0
A28: O-tec | B28: Surat | C28: ACS TEXTILES (BANGLADESH) LTD | D28: OTHERS | F28: 0 | G28: 0 | H28: 0
A29: Enterprise | B29: Surat | C29: ADIYA DESIGNER | D29: NAKUL JI | E29: 60 Days | F29: 100000 | G29: 0 | H29: {=XLOOKUP(C:C,Sheet3!A:A,Sheet3!B:B)} -> #N/A
A30: O-tec | B30: Surat | C30: ADIYA DESIGNER | D30: NAKUL JI | E30: 60 Days | F30: 4000000 | G30: 2502447 | H30: {=XLOOKUP(C:C,Sheet3!A:A,Sheet3!B:B)} -> #N/A
A31: O-tec | B31: Surat | C31: ADVANCE FORM DEBTORS | D31: OTHERS | F31: 0 | G31: -1956 | H31: 0
A32: O-tec | B32: Surat | C32: AEROLAM DECORATIVES LLP | D32: OTHERS | F32: 0 | G32: 0 | H32: 0
A33: O-tec | B33: Surat | C33: AGANSA PRIMATAMA. PT | D33: OTHERS | F33: 0 | G33: 0 | H33: 0
A34: O-tec | B34: Surat | C34: AIRDOT FAB TEX | D34: OTHERS | F34: 0 | G34: 0 | H34: 0
A35: O-tec | B35: Surat | C35: AISHAWARYA CREATIONS | D35: MANMOHAN JI | E35: 30 Days | F35: 600000 | G35: 25025 | H35: {=XLOOKUP(C:C,Sheet3!A:A,Sheet3!B:B)} -> #N/A
A36: O-tec | B36: Noida | C36: AISHAWARYA CREATIONS | D36: MANMOHAN JI | E36: 30 Days | F36: 1241782 | G36: 186735 | H36: {=XLOOKUP(C:C,Sheet3!A:A,Sheet3!B:B)} -> #N/A
A37: Enterprise | B37: Surat | C37: AJANTA DIGITAL INDUSTRIES | D37: DHANANJAY | F37: 300000 | G37: 0 | H37: {=XLOOKUP(C:C,Sheet3!A:A,Sheet3!B:B)} -> #N/A
A38: O-tec | B38: Surat | C38: AJANTA DIGITAL INDUSTRIES-AHMEDABAD | D38: DHANANJAY | F38: 0 | G38: 0 | H38: {=XLOOKUP(C:C,Sheet3!A:A,Sheet3!B:B)} -> #N/A
A39: O-tec | B39: Surat | C39: AJANTA DIGITAL INDUSTRIES-SURAT | D39: DHANANJAY | F39: 650000 | G39: 0 | H39: {=XLOOKUP(C:C,Sheet3!A:A,Sheet3!B:B)} -> #N/A
A40: O-tec | B40: Surat | C40: AKASH PRASANNAKUMAR SHAH- DOLPHIN DIGITAL | D40: OTHERS | F40: 0 | G40: 0 | H40: 0
A41: O-tec | B41: Surat | C41: AKHAND DIGITEX | D41: OTHERS | E41: 15 Days | F41: 450000 | G41: 0 | H41: {=XLOOKUP(C:C,Sheet3!A:A,Sheet3!B:B)} -> #N/A
A42: O-tec | B42: Surat | C42: AKLAVYA INDUSTRIES PVT.LTD. | D42: OTHERS | E42: 30 Days | F42: 0 | G42: 0 | H42: 0
A43: O-tec | B43: Surat | C43: AKSHAR PRINTS | D43: OTHERS | F43: 0 | G43: 0 | H43: 0
A44: O-tec | B44: Surat | C44: AKSHAR PRINTS-MACHINE | D44: OTHERS | F44: 0 | G44: 0 | H44: 0
A45: O-tec | B45: Surat | C45: ALOK FABRICS | D45: DHANANJAY | E45: 60 Days | F45: 550000 | G45: 40710 | H45: {=XLOOKUP(C:C,Sheet3!A:A,Sheet3!B:B)} -> #N/A
A46: O-tec | B46: Noida | C46: ALOK TEXTILE MILL | D46: KHURSHID JI | F46: 0 | G46: 0 | H46: {=XLOOKUP(C:C,Sheet3!A:A,Sheet3!B:B)} -> #N/A
A47: O-tec | B47: Surat | C47: ALOKA EXPORTS | D47: OTHERS | F47: 1210000 | G47: -510328 | H47: 0
A48: O-tec | B48: Noida | C48: ALOKA EXPORTS | D48: OTHERS | F48: 0 | G48: 0 | H48: 0
A49: O-tec | B49: Surat | C49: ALPHA DIGITAL | D49: OTHERS | F49: 4000 | G49: 0 | H49: {=XLOOKUP(C:C,Sheet3!A:A,Sheet3!B:B)} -> #N/A
A50: Enterprise | B50: Noida | C50: AMAAYRA DIGITAL PRIVATE LIMITED | D50: MANMOHAN JI | F50: 0 | G50: 0 | H50: {=XLOOKUP(C:C,Sheet3!A:A,Sheet3!B:B)} -> #N/A
A51: O-tec | B51: Noida | C51: AMAAYRA DIGITAL PRIVATE LIMITED | D51: MANMOHAN JI | E51: 45 Days | F51: 1989490 | G51: 2085525.5 | H51: {=XLOOKUP(C:C,Sheet3!A:A,Sheet3!B:B)} -> #N/A
A52: O-tec | B52: Surat | C52: AMAAYRA DIGITAL PRIVATE LIMITED-MACHINE | D52: MANMOHAN JI | F52: 0 | G52: 0 | H52: {=XLOOKUP(C:C,Sheet3!A:A,Sheet3!B:B)} -> #N/A
A53: O-tec | B53: Noida | C53: AMAAYRA DIGITAL PRIVATE LIMITED-MACHINE | D53: MANMOHAN JI | F53: 0 | G53: 2595000 | H53: {=XLOOKUP(C:C,Sheet3!A:A,Sheet3!B:B)} -> #N/A
A54: O-tec | B54: Noida | C54: AMANDEEP TEXTILES | D54: MANMOHAN JI | E54: 45 Days | F54: 0 | G54: 0 | H54: {=XLOOKUP(C:C,Sheet3!A:A,Sheet3!B:B)} -> #N/A
A55: O-tec | B55: Surat | C55: AMANDEEP TEXTILES-MACHINE | D55: MANMOHAN JI | F55: 0 | G55: 0 | H55: {=XLOOKUP(C:C,Sheet3!A:A,Sheet3!B:B)} -> #N/A
A56: O-tec | B56: Surat | C56: AMAR CREATION | D56: PURAV SHAH | F56: 0 | G56: 0 | H56: {=XLOOKUP(C:C,Sheet3!A:A,Sheet3!B:B)} -> #N/A
A57: O-tec | B57: Surat | C57: AMARASHA DIGITAL PRINTS PRIVATE LIMITED | D57: NAKUL JI | E57: 30 Days | F57: 900000 | G57: 0 | H57: {=XLOOKUP(C:C,Sheet3!A:A,Sheet3!B:B)} -> #N/A
A58: O-tec | B58: Surat | C58: AMARSONS IMPEX | D58: OTHERS | F58: 0 | G58: 0 | H58: 0
A59: O-tec | B59: Surat | C59: AMBE TEXTILES | D59: OTHERS | F59: 0 | G59: 0 | H59: 0
A60: Enterprise | B60: Noida | C60: AMBIKA INTERNATIONAL | D60: KHURSHID JI | E60: 45 Days | F60: 414745 | G60: 0 | H60: {=XLOOKUP(C:C,Sheet3!A:A,Sheet3!B:B)} -> #N/A
A61: Enterprise | B61: Surat | C61: AMBIKA INTERNATIONAL | D61: KHURSHID JI | F61: 0 | G61: 0 | H61: {=XLOOKUP(C:C,Sheet3!A:A,Sheet3!B:B)} -> #N/A
A62: O-tec | B62: Surat | C62: AMBIKA INTERNATIONAL | D62: KHURSHID JI | F62: 0 | G62: 0 | H62: {=XLOOKUP(C:C,Sheet3!A:A,Sheet3!B:B)} -> #N/A
A63: O-tec | B63: Noida | C63: AMBIKA INTERNATIONAL | D63: KHURSHID JI | E63: 45 Days | F63: 500000 | G63: 0 | H63: {=XLOOKUP(C:C,Sheet3!A:A,Sheet3!B:B)} -> #N/A
A64: O-tec | B64: Surat | C64: AMIT CORPORATION | D64: OTHERS | F64: 0 | G64: 0 | H64: 0
A65: Enterprise | B65: Surat | C65: AMIT DIGITAL PRINT | D65: NAKUL JI | E65: 1 Days | F65: 300000 | G65: 0 | H65: {=XLOOKUP(C:C,Sheet3!A:A,Sheet3!B:B)} -> #N/A
A66: O-tec | B66: Surat | C66: AMIT DIGITAL PRINT | D66: NAKUL JI | F66: 500000 | G66: 0 | H66: {=XLOOKUP(C:C,Sheet3!A:A,Sheet3!B:B)} -> #N/A
A67: O-tec | B67: Surat | C67: AMTEX DYE CHEM INDUSTRIES | D67: OTHERS | F67: 0 | G67: 0 | H67: {=XLOOKUP(C:C,Sheet3!A:A,Sheet3!B:B)} -> #N/A
A68: O-tec | B68: Noida | C68: ANAND DYERS | D68: MANMOHAN JI | E68: 30 Days | F68: 1807430 | G68: 222060 | H68: {=XLOOKUP(C:C,Sheet3!A:A,Sheet3!B:B)} -> #N/A
A69: O-tec | B69: Surat | C69: ANAND DYERS-MACHINE | D69: OTHERS | F69: 2005000 | G69: 0 | H69: 0
A70: O-tec | B70: Surat | C70: ANANYA CREATION | D70: OTHERS | F70: 200000 | G70: 137521.34 | H70: {=XLOOKUP(C:C,Sheet3!A:A,Sheet3!B:B)} -> #N/A
A71: Enterprise | B71: Surat | C71: ANAYAA DIGITAL LLP | D71: NAKUL JI | E71: 40 Days | F71: 300000 | G71: 0 | H71: {=XLOOKUP(C:C,Sheet3!A:A,Sheet3!B:B)} -> #N/A
A72: O-tec | B72: Surat | C72: ANAYAA DIGITAL LLP | D72: NAKUL JI | E72: 40 Days | F72: 1605000 | G72: 575510 | H72: {=XLOOKUP(C:C,Sheet3!A:A,Sheet3!B:B)} -> #N/A
A73: O-tec | B73: Surat | C73: ANAYAA DIGITAL LLP(MACHINE) | D73: OTHERS | F73: 0 | G73: 0 | H73: 0
A74: O-tec | B74: Surat | C74: ANGARIKA DIGITEX PVT LTD | D74: KARAN SIR | E74: 75 Days | F74: 20000000 | G74: 19419409 | H74: {=XLOOKUP(C:C,Sheet3!A:A,Sheet3!B:B)} -> #N/A
A75: O-tec | B75: Surat | C75: ANGARIKA DIGITEX PVT LTD-MACHINE | D75: KARAN SIR | F75: 0 | G75: 0 | H75: 0
A76: O-tec | B76: Surat | C76: ANIL | D76: OTHERS | F76: 0 | G76: 0 | H76: 0
A77: Enterprise | B77: Surat | C77: ANISHA THE COLOUR CO. | D77: UMESH JI | E77: 15 | F77: 10000000 | G77: 0 | H77: {=XLOOKUP(C:C,Sheet3!A:A,Sheet3!B:B)} -> #N/A
A78: O-tec | B78: Surat | C78: ANISHA THE COLOUR CO. | D78: UMESH JI | E78: 15 Days | F78: 10000000 | G78: 1632087 | H78: {=XLOOKUP(C:C,Sheet3!A:A,Sheet3!B:B)} -> #N/A
A79: O-tec | B79: Surat | C79: ANISHA THE COLOUR CO.- MACHINE | D79: UMESH JI | F79: 0 | G79: 0 | H79: {=XLOOKUP(C:C,Sheet3!A:A,Sheet3!B:B)} -> #N/A
A80: O-tec | B80: Surat | C80: ANJANI SYNTHETICS LIMITED | D80: OTHERS | F80: 182000 | G80: 0 | H80: 0
A81: O-tec | B81: Surat | C81: ANJANI SYNTHETICS LIMITED-MACHINE | D81: OTHERS | F81: 0 | G81: 0 | H81: 0
A82: O-tec | B82: Surat | C82: ANKIT CREATION | D82: OTHERS | F82: 0 | G82: 0 | H82: 0
A83: O-tec | B83: Surat | C83: ANSARI MAKBULALAM MOHMEDYASHIN | D83: OTHERS | F83: 0 | G83: 0 | H83: 0
A84: Enterprise | B84: Surat | C84: ANSH DIGITEX LLP | D84: DHANANJAY | E84: 90 Days | F84: 0 | G84: 0 | H84: {=XLOOKUP(C:C,Sheet3!A:A,Sheet3!B:B)} -> #N/A
A85: O-tec | B85: Surat | C85: ANSH DIGITEX LLP | D85: DHANANJAY | E85: 90 Days | F85: 1600000 | G85: 0 | H85: {=XLOOKUP(C:C,Sheet3!A:A,Sheet3!B:B)} -> #N/A
A86: Enterprise | B86: Surat | C86: ANUPAM CREATION PVT LTD | D86: AAYUSH SIR | E86: 1 | F86: 5100000 | G86: 0 | H86: {=XLOOKUP(C:C,Sheet3!A:A,Sheet3!B:B)} -> #N/A
A87: O-tec | B87: Surat | C87: ANUPAM CREATION PVT LTD | D87: AAYUSH SIR | E87: 1 Days | F87: 5100000 | G87: 1874108 | H87: {=XLOOKUP(C:C,Sheet3!A:A,Sheet3!B:B)} -> #N/A
A88: O-tec | B88: Noida | C88: ANUPAM CREATION PVT LTD | D88: AAYUSH SIR | E88: 1 Days | F88: 0 | G88: 0 | H88: {=XLOOKUP(C:C,Sheet3!A:A,Sheet3!B:B)} -> #N/A
A89: O-tec | B89: Surat | C89: ANUPAM CREATION PVT LTD-MACHINE | D89: AAYUSH SIR | F89: 0 | G89: 0 | H89: 0
A90: O-tec | B90: Surat | C90: APEX IMPEX | D90: OTHERS | F90: 200000 | G90: 578630 | H90: {=XLOOKUP(C:C,Sheet3!A:A,Sheet3!B:B)} -> #N/A
A91: O-tec | B91: Surat | C91: APEX IMPEX-Amit Digital Prints | D91: OTHERS | F91: 0 | G91: 0 | H91: 0
A92: O-tec | B92: Surat | C92: APK ENGINEERING | D92: OTHERS | F92: 0 | G92: 0 | H92: 0
A93: Enterprise | B93: Surat | C93: APOLLO DIGITEX PVT.LTD | D93: AAYUSH SIR | E93: 75 | F93: 10000000 | G93: 0 | H93: 0
A94: O-tec | B94: Surat | C94: APOLLO DIGITEX PVT.LTD | D94: AAYUSH SIR | E94: 90 Days | F94: 10000000 | G94: 5769248 | H94: 0
A95: O-tec | B95: Surat | C95: APOLLO DIGITEX PVT.LTD-MACHINE | D95: AAYUSH SIR | E95: 30 Days | F95: 0 | G95: 2003380 | H95: 0
A96: Enterprise | B96: Noida | C96: APOLLO DIGITEX PRIVATE LIMITED | D96: AAYUSH SIR | E96: 90 Days | F96: 950000 | G96: 0 | H96: {=XLOOKUP(C:C,Sheet3!A:A,Sheet3!B:B)} -> #N/A
A97: O-tec | B97: Noida | C97: APOLLO DIGITEX PRIVATE LIMITED | D97: AAYUSH SIR | E97: 90 Days | F97: 3085000 | G97: 2124078.9 | H97: {=XLOOKUP(C:C,Sheet3!A:A,Sheet3!B:B)} -> #N/A
A98: O-tec | B98: Surat | C98: APSARA SILKS | D98: OTHERS | F98: 63000 | G98: 0 | H98: 0
A99: O-tec | B99: Surat | C99: ARA DIGITAL PRINTS | D99: NAKUL JI | E99: 60 Days | F99: 700000 | G99: 0 | H99: {=XLOOKUP(C:C,Sheet3!A:A,Sheet3!B:B)} -> #N/A
A100: O-tec | B100: Surat | C100: ARCHNA DYEING & PRINTING MILLS P LTD | D100: OTHERS | E100: 7 Days | F100: 0 | G100: 0 | H100: {=XLOOKUP(C:C,Sheet3!A:A,Sheet3!B:B)} -> #N/A
...
